LICENSE
README.md
setup.py
bayesian_safety_validation/__init__.py
bayesian_safety_validation/acq_max.py
bayesian_safety_validation/bayesian_safety_validation.py
bayesian_safety_validation/sample_space.py
bayesian_safety_validation/utils.py
bayesian_safety_validation.egg-info/PKG-INFO
bayesian_safety_validation.egg-info/SOURCES.txt
bayesian_safety_validation.egg-info/dependency_links.txt
bayesian_safety_validation.egg-info/entry_points.txt
bayesian_safety_validation.egg-info/requires.txt
bayesian_safety_validation.egg-info/top_level.txt
tests/test_bayesian_safty_validation.py