Metadata-Version: 2.1
Name: bayesian_safety_validation
Version: 0.0.1
Summary: Estimate failure probability for  binary-valued black-box system
Home-page: https://github.com/loriskong/BayesianSafetyValidation
Author: Loris Kong
Author-email: imloriskong@gmail.com
License: MIT License
Classifier: License :: OSI Approved :: MIT License
Classifier: Programming Language :: Python
Classifier: Programming Language :: Python :: 3
Classifier: Programming Language :: Python :: 3.9
Classifier: Programming Language :: Python :: Implementation :: CPython
Classifier: Programming Language :: Python :: Implementation :: PyPy
Requires-Python: >=3.9
License-File: LICENSE
Requires-Dist: matplotlib>=3.8.4
Requires-Dist: numpy>=1.26.1
Requires-Dist: pytest>=7.4.4
Requires-Dist: typing_extensions>=4.10.0
Requires-Dist: bayesian-optimization>=1.4.3
Requires-Dist: scikit-learn>=1.4.0
Requires-Dist: scipy>=1.13.0
